README.rst
cheesecake_index
setup.py
Cheesecake.egg-info/PKG-INFO
Cheesecake.egg-info/SOURCES.txt
Cheesecake.egg-info/dependency_links.txt
Cheesecake.egg-info/entry_points.txt
Cheesecake.egg-info/top_level.txt
cheesecake/__init__.py
cheesecake/ast_pp.py
cheesecake/cheesecake_index.py
cheesecake/codeparser.py
cheesecake/logger.py
cheesecake/model.py
cheesecake/pep8.py
cheesecake/subprocess.py
cheesecake/util.py