Metadata-Version: 1.0
Name: Cheesecake
Version: 0.6.2
Summary: Computes "goodness" index for Python packages based on various empirical "kwalitee" factors
Home-page: http://pycheesecake.org/
Author: Grig Gheorghiu and Michal Kwiatkowski
Author-email: grig@gheorghiu.net and michal@trivas.pl
License: PSF
Keywords: cheesecake quality index kwalitee cheeseshop pypi
Platform: UNKNOWN
